testai/__init__.cp310-win_amd64.pyd
testai/add.cp310-win_amd64.pyd
testai-0.0.14.dist-info/METADATA
testai-0.0.14.dist-info/WHEEL
testai-0.0.14.dist-info/top_level.txt
testai-0.0.14.dist-info/RECORD
